MANIFEST.in
README.md
setup.cfg
setup.py
agenda/__init__.py
agenda.egg-info/PKG-INFO
agenda.egg-info/SOURCES.txt
agenda.egg-info/dependency_links.txt
agenda.egg-info/requires.txt
agenda.egg-info/top_level.txt